enterprise/__init__.py
enterprise/constants.py
enterprise/pulsar.py
enterprise/pulsar_inflate.py
enterprise/version.py
enterprise/datafiles/pulsar_distances.json
enterprise/datafiles/ephemeris/jupiter-orbel-mjd.npy
enterprise/datafiles/ephemeris/jupiter-orbel-v2-mjd.npy
enterprise/datafiles/ephemeris/jupiter-orbel-v2-xyz-svd.npy
enterprise/datafiles/ephemeris/jupiter-orbel-xyz-svd.npy
enterprise/datafiles/ephemeris/jupiter-orbel-xyz.npy
enterprise/datafiles/ephemeris/jupiter-setIII-Dcov-DE434.npy
enterprise/datafiles/ephemeris/jupiter-setIII-Dcov-DE438.npy
enterprise/datafiles/ephemeris/jupiter-setIII-mjd.npy
enterprise/datafiles/ephemeris/jupiter-setIII-xyz-svd.npy
enterprise/datafiles/ephemeris/jupiter-setIII_1980-Mconv.npy
enterprise/datafiles/ephemeris/jupiter-setIII_1980-mjd.npy
enterprise/datafiles/ephemeris/jupiter-setIII_1980-xyz-svd.npy
enterprise/datafiles/ephemeris/jupiter-setIII_1980-xyz.npy
enterprise/datafiles/ephemeris/saturn-orbel-mjd.npy
enterprise/datafiles/ephemeris/saturn-orbel-v2-xyz-svd.npy
enterprise/datafiles/ephemeris/saturn-orbel-xyz-svd.npy
enterprise/datafiles/ephemeris/saturn-setIII-xyz-svd.npy
enterprise/datafiles/ephemeris/saturn-setIII_1980-Mconv.npy
enterprise/datafiles/ephemeris/saturn-setIII_1980-mjd.npy
enterprise/datafiles/ephemeris/saturn-setIII_1980-xyz-svd.npy
enterprise/datafiles/ephemeris/saturn-setIII_1980-xyz.npy
enterprise/datafiles/mdc_open1/J0030+0451.par
enterprise/datafiles/mdc_open1/J0030+0451.tim
enterprise/datafiles/mdc_open1/J0218+4232.par
enterprise/datafiles/mdc_open1/J0218+4232.tim
enterprise/datafiles/mdc_open1/J0437-4715.par
enterprise/datafiles/mdc_open1/J0437-4715.tim
enterprise/datafiles/mdc_open1/J0613-0200.par
enterprise/datafiles/mdc_open1/J0613-0200.tim
enterprise/datafiles/mdc_open1/J0621+1002.par
enterprise/datafiles/mdc_open1/J0621+1002.tim
enterprise/datafiles/mdc_open1/J0711-6830.par
enterprise/datafiles/mdc_open1/J0711-6830.tim
enterprise/datafiles/mdc_open1/J0751+1807.par
enterprise_pulsar-3.4.4.dist-info/AUTHORS.rst
enterprise_pulsar-3.4.4.dist-info/LICENSE
enterprise_pulsar-3.4.4.dist-info/METADATA
enterprise_pulsar-3.4.4.dist-info/WHEEL
enterprise_pulsar-3.4.4.dist-info/top_level.txt
enterprise_pulsar-3.4.4.dist-info/RECORD
