Metadata-Version: 2.1
Name: enterprise-pulsar
Version: 3.4.4
Summary: ENTERPRISE (Enhanced Numerical Toolbox Enabling a Robust PulsaR Inference SuitE)
Home-page: https://github.com/nanograv/enterprise
Author: Justin A. Ellis
Author-email: justin.ellis18@gmail.com
License: MIT license
Keywords: enterprise
Classifier: Development Status :: 4 - Beta
Classifier: Intended Audience :: Developers
Classifier: Intended Audience :: Science/Research
Classifier: License :: OSI Approved :: MIT License
Classifier: Natural Language :: English
Classifier: Programming Language :: Python :: 3
Classifier: Programming Language :: Python :: 3.8
Classifier: Programming Language :: Python :: 3.9
Classifier: Programming Language :: Python :: 3.10
Classifier: Programming Language :: Python :: 3.11
Classifier: Programming Language :: Python :: 3.12
Classifier: Topic :: Scientific/Engineering :: Astronomy
Classifier: Topic :: Scientific/Engineering :: Physics
Requires-Python: >=3.8, <3.13
License-File: LICENSE
License-File: AUTHORS.rst
Requires-Dist: numpy>=1.16.3
Requires-Dist: scipy>=1.2.0
Requires-Dist: ephem>=3.7.6.0
Requires-Dist: healpy>=1.14.0
Requires-Dist: scikit-sparse>=0.4.5
Requires-Dist: pyarrow>=17.0.0
